moj_pakiet
