Metadata-Version: 1.0
Name: pierwszy-pakiet-pajtona
Version: 0.3
Summary: First PythonPackage
Home-page: UNKNOWN
Author: Unknown
Author-email: unknown@gmail.com
License: UNKNOWN
Platform: UNKNOWN
